sqlalchemy_pymssql_sybase/__init__.py
sqlalchemy_pymssql_sybase/pymssql.py
sqlalchemy_pymssql_sybase-0.0.1.dev0.data/data/requirements.txt
sqlalchemy_pymssql_sybase-0.0.1.dev0.dist-info/LICENSE
sqlalchemy_pymssql_sybase-0.0.1.dev0.dist-info/METADATA
sqlalchemy_pymssql_sybase-0.0.1.dev0.dist-info/WHEEL
sqlalchemy_pymssql_sybase-0.0.1.dev0.dist-info/entry_points.txt
sqlalchemy_pymssql_sybase-0.0.1.dev0.dist-info/top_level.txt
sqlalchemy_pymssql_sybase-0.0.1.dev0.dist-info/RECORD
