Metadata-Version: 2.1
Name: sqlalchemy-pymssql-sybase
Version: 0.0.1.dev0
Summary: SAP ASE (Sybase) Connector for SQLAlchemy using PyMsSql
Home-page: https://github.com/gordthompson/sqlalchemy-pymssql-sybase
Author: Giovany Vega
Author-email: aleph.omega@gmail.com
License: MIT
Project-URL: Documentation, https://github.com/gordthompson/sqlalchemy-pymssql-sybase/wiki
Project-URL: Source, https://github.com/gordthompson/sqlalchemy-pymssql-sybase
Project-URL: Tracker, https://github.com/gordthompson/sqlalchemy-pymssql-sybase/issues
Keywords: ASE SAP SQLAlchemy Sybase PyMSSql
Classifier: Development Status :: 3 - Alpha
Classifier: Intended Audience :: Developers
Classifier: License :: OSI Approved :: MIT License
Classifier: Programming Language :: Python
Classifier: Programming Language :: Python :: 3
Classifier: Programming Language :: Python :: Implementation :: CPython
Classifier: Topic :: Database :: Front-Ends
Classifier: Operating System :: OS Independent
License-File: LICENSE
Requires-Dist: pymssql >=2.2.8
Requires-Dist: SQLAlchemy >=2.0.0
